resonfit/__init__.py
resonfit/core/__init__.py
resonfit/core/base.py
resonfit/core/models.py
resonfit/core/pipeline.py
resonfit/fitting/__init__.py
resonfit/fitting/base.py
resonfit/fitting/methods/__init__.py
resonfit/fitting/methods/cpzm.py
resonfit/fitting/methods/dcm.py
resonfit/fitting/methods/inverse.py
resonfit/preprocessing/__init__.py
resonfit/preprocessing/base.py
resonfit/preprocessing/delay.py
resonfit/preprocessing/normalization.py
resonfit/visualization/__init__.py
resonfit/visualization/plotter.py
resonfit-0.2.0.dist-info/licenses/LICENSE
resonfit-0.2.0.dist-info/METADATA
resonfit-0.2.0.dist-info/WHEEL
resonfit-0.2.0.dist-info/top_level.txt
resonfit-0.2.0.dist-info/RECORD
