Metadata-Version: 2.4
Name: resonfit
Version: 0.2.0
Summary: A modular tool for fitting superconducting resonator data
Home-page: https://github.com/ydkim0119/ResonFit
Author: ydkim0119
Author-email: guaolbux@gmail.com
Classifier: Programming Language :: Python :: 3
Classifier: License :: OSI Approved :: MIT License
Classifier: Operating System :: OS Independent
Classifier: Topic :: Scientific/Engineering :: Physics
Requires-Python: >=3.8
License-File: LICENSE
Requires-Dist: numpy>=1.20.0
Requires-Dist: scipy>=1.7.0
Requires-Dist: matplotlib>=3.4.0
Provides-Extra: dev
Requires-Dist: pytest>=6.0.0; extra == "dev"
Requires-Dist: pytest-cov>=2.12.0; extra == "dev"
Requires-Dist: black>=21.5b2; extra == "dev"
Requires-Dist: sphinx>=4.0.0; extra == "dev"
Requires-Dist: sphinx-rtd-theme>=0.5.0; extra == "dev"
Requires-Dist: ipykernel>=6.0.0; extra == "dev"
Dynamic: author
Dynamic: author-email
Dynamic: classifier
Dynamic: description
Dynamic: description-content-type
Dynamic: home-page
Dynamic: license-file
Dynamic: provides-extra
Dynamic: requires-dist
Dynamic: requires-python
Dynamic: summary
